linkai/__init__.py
linkai/_common/__init__.py
linkai/_common/log.py
linkai/api/__init__.py
linkai/api/client/__init__.py
linkai/api/client/client.py
linkai-0.0.5.0.dist-info/METADATA
linkai-0.0.5.0.dist-info/WHEEL
linkai-0.0.5.0.dist-info/top_level.txt
linkai-0.0.5.0.dist-info/RECORD
